neutron_lbaas_dashboard/__init__.py
neutron_lbaas_dashboard/karma.conf.js
neutron_lbaas_dashboard/post_install.sh
neutron_lbaas_dashboard/api/__init__.py
neutron_lbaas_dashboard/api/rest/__init__.py
neutron_lbaas_dashboard/api/rest/barbican.py
neutron_lbaas_dashboard/api/rest/nlbaasv2.py
neutron_lbaas_dashboard/dashboards/__init__.py
neutron_lbaas_dashboard/dashboards/project/__init__.py
neutron_lbaas_dashboard/dashboards/project/ngloadbalancersv2/__init__.py
neutron_lbaas_dashboard/dashboards/project/ngloadbalancersv2/panel.py
neutron_lbaas_dashboard/dashboards/project/ngloadbalancersv2/urls.py
neutron_lbaas_dashboard/dashboards/project/ngloadbalancersv2/views.py
neutron_lbaas_dashboard/dashboards/project/ngloadbalancersv2/templates/ngloadbalancersv2/index.html
neutron_lbaas_dashboard/enabled/_1481_project_ng_loadbalancersv2_panel.py
neutron_lbaas_dashboard/enabled/__init__.py
neutron_lbaas_dashboard/locale/de/LC_MESSAGES/django.po
neutron_lbaas_dashboard/locale/de/LC_MESSAGES/djangojs.po
neutron_lbaas_dashboard/locale/en_GB/LC_MESSAGES/django.po
neutron_lbaas_dashboard/locale/en_GB/LC_MESSAGES/djangojs.po
neutron_lbaas_dashboard/locale/fr/LC_MESSAGES/django.po
neutron_lbaas_dashboard/locale/fr/LC_MESSAGES/djangojs.po
neutron_lbaas_dashboard/locale/id/LC_MESSAGES/django.po
neutron_lbaas_dashboard/locale/id/LC_MESSAGES/djangojs.po
neutron_lbaas_dashboard/locale/ja/LC_MESSAGES/django.po
neutron_lbaas_dashboard/locale/ja/LC_MESSAGES/djangojs.po
neutron_lbaas_dashboard/locale/ko_KR/LC_MESSAGES/django.po
neutron_lbaas_dashboard/locale/ko_KR/LC_MESSAGES/djangojs.po
neutron_lbaas_dashboard/locale/pt_BR/LC_MESSAGES/django.po
neutron_lbaas_dashboard/locale/ru/LC_MESSAGES/django.po
neutron_lbaas_dashboard/locale/ru/LC_MESSAGES/djangojs.po
neutron_lbaas_dashboard/locale/tr_TR/LC_MESSAGES/djangojs.po
neutron_lbaas_dashboard/locale/zh_CN/LC_MESSAGES/django.po
neutron_lbaas_dashboard/locale/zh_CN/LC_MESSAGES/djangojs.po
neutron_lbaas_dashboard-6.0.1.dist-info/DESCRIPTION.rst
neutron_lbaas_dashboard-6.0.1.dist-info/METADATA
neutron_lbaas_dashboard-6.0.1.dist-info/RECORD
neutron_lbaas_dashboard-6.0.1.dist-info/WHEEL
neutron_lbaas_dashboard-6.0.1.dist-info/metadata.json
neutron_lbaas_dashboard-6.0.1.dist-info/pbr.json
neutron_lbaas_dashboard-6.0.1.dist-info/top_level.txt
