Metadata-Version: 2.0
Name: neutron-lbaas-dashboard
Version: 6.0.1
Summary: Horizon panels for Neutron LBaaS
Home-page: https://docs.openstack.org/neutron-lbaas-dashboard/latest/
Author: OpenStack
Author-email: openstack-discuss@lists.openstack.org
License: UNKNOWN
Platform: UNKNOWN
Classifier: Environment :: OpenStack
Classifier: Intended Audience :: Information Technology
Classifier: Intended Audience :: System Administrators
Classifier: License :: OSI Approved :: Apache Software License
Classifier: Operating System :: POSIX :: Linux
Classifier: Programming Language :: Python
Classifier: Programming Language :: Python :: 2
Classifier: Programming Language :: Python :: 2.7
Requires-Dist: Babel (!=2.4.0,>=2.3.4)
Requires-Dist: horizon (>=14.0.0.0b3)
Requires-Dist: oslo.log (>=3.36.0)
Requires-Dist: pbr (!=2.1.0,>=2.0.0)
Requires-Dist: python-barbicanclient (>=4.5.2)
